transferfile/__init__.py
transferfile/ftp.py
transferfile/rsync.py
transferfile/scp.py
transferfile/sftp.py
transferfile/transfile_interface.py
transferfile-0.7.dist-info/LICENSE
transferfile-0.7.dist-info/METADATA
transferfile-0.7.dist-info/WHEEL
transferfile-0.7.dist-info/top_level.txt
transferfile-0.7.dist-info/RECORD
